fix-rackspace
setup.py
littlechef_rackspace/__init__.py
littlechef_rackspace/api.py
littlechef_rackspace/commands.py
littlechef_rackspace/deploy.py
littlechef_rackspace/lib.py
littlechef_rackspace/runner.py
littlechef_rackspace.egg-info/PKG-INFO
littlechef_rackspace.egg-info/SOURCES.txt
littlechef_rackspace.egg-info/dependency_links.txt
littlechef_rackspace.egg-info/requires.txt
littlechef_rackspace.egg-info/top_level.txt
test/test_api.py
test/test_commands.py
test/test_deploy.py
test/test_runner.py