Metadata-Version: 1.1
Name: littlechef-rackspace
Version: 0.7
Summary: Scripts for bootstrapping Rackspace Cloud Servers with Littlechef
Home-page: http://github.com/tildedave/littlechef-rackspace
Author: Dave King
Author-email: tildedave@gmail.com
License: UNKNOWN
Download-URL: http://github.com/tildedave/littlechef-rackspace/archives/master
Keywords: chef,rackspace,openstack,devops,operations
Platform: UNKNOWN
Classifier: Programming Language :: Python
Classifier: Environment :: Console
Classifier: Intended Audience :: Developers
